setup.py
Pygling/Env.py
Pygling/Globals.py
Pygling/Location.py
Pygling/Makefile.py
Pygling/Workspace.py
Pygling/__init__.py
Pygling/__main__.py
Pygling/Builder/VisualStudio.py
Pygling/Builder/Xcode.py
Pygling/Builder/__init__.py
Pygling/Generator/Generator.py
Pygling/Generator/Template.py
Pygling/Generator/__init__.py
Pygling/Generator/Eclipse/Android.py
Pygling/Generator/Eclipse/__init__.py
Pygling/Generator/Extensions/Qt.py
Pygling/Generator/Extensions/RTTI.py
Pygling/Generator/Extensions/__init__.py
Pygling/Generator/Make/Android.py
Pygling/Generator/Make/Flash.py
Pygling/Generator/Make/HTML5.py
Pygling/Generator/Make/Make.py
Pygling/Generator/Make/__init__.py
Pygling/Generator/VisualStudio/Windows.py
Pygling/Generator/VisualStudio/__init__.py
Pygling/Generator/VisualStudio/VCX/Configuration.py
Pygling/Generator/VisualStudio/VCX/Filters.py
Pygling/Generator/VisualStudio/VCX/Groups.py
Pygling/Generator/VisualStudio/VCX/ID.py
Pygling/Generator/VisualStudio/VCX/Project.py
Pygling/Generator/VisualStudio/VCX/Solution.py
Pygling/Generator/VisualStudio/VCX/WindowsProject.py
Pygling/Generator/VisualStudio/VCX/__init__.py
Pygling/Generator/Xcode/MacOS.py
Pygling/Generator/Xcode/Xcode5.py
Pygling/Generator/Xcode/__init__.py
Pygling/Generator/Xcode/iOS.py
Pygling/Generator/Xcode/PBX/BuildConfiguration.py
Pygling/Generator/Xcode/PBX/BuildPhases.py
Pygling/Generator/Xcode/PBX/ConfigurationList.py
Pygling/Generator/Xcode/PBX/Files.py
Pygling/Generator/Xcode/PBX/Group.py
Pygling/Generator/Xcode/PBX/ObjectList.py
Pygling/Generator/Xcode/PBX/Objects.py
Pygling/Generator/Xcode/PBX/Project.py
Pygling/Generator/Xcode/PBX/Resource.py
Pygling/Generator/Xcode/PBX/Targets.py
Pygling/Generator/Xcode/PBX/__init__.py
Pygling/Platform/Android.py
Pygling/Platform/MacOS.py
Pygling/Platform/Platform.py
Pygling/Platform/Unix.py
Pygling/Platform/Windows.py
Pygling/Platform/Xcode.py
Pygling/Platform/__init__.py
Pygling/Platform/iOS.py
Pygling/Target/Executable.py
Pygling/Target/File.py
pygling.egg-info/PKG-INFO
pygling.egg-info/SOURCES.txt
pygling.egg-info/dependency_links.txt
pygling.egg-info/not-zip-safe
pygling.egg-info/top_level.txt