Metadata-Version: 1.0
Name: pygling
Version: 0.8.9
Summary: Pygling is a C++ workspace generator written in Python.
Home-page: https://github.com/dmsovetov/Pygling
Author: Dmitry Sovetov
Author-email: dmsovetov@gmail.com
License: MIT
Platform: UNKNOWN
